greetings/__init__.py
greetings/hello.py
greetings/world.py
hola-1.1.54.dist-info/METADATA
hola-1.1.54.dist-info/WHEEL
hola-1.1.54.dist-info/top_level.txt
hola-1.1.54.dist-info/RECORD
