Metadata-Version: 2.1
Name: hola
Version: 1.1.54
Summary: This is the summary (or short description)
Home-page: UNKNOWN
Author: smd
Author-email: "asdf,df" <aasimD@redf.com>
Maintainer-email: trentm@gmail.com
License: UNKNOWN
Download-URL: http://www.ggogasd.fom
Project-URL: sadsdsddfgsfgdf, https://www.goog.com
Project-URL: safd, https://www.google.com
Keywords: sample test blah
Platform: linux_x86_32
Classifier: Programming Language :: Python :: 3
Classifier: Operating System :: OS Independent
Requires-Python: >2.9
Requires-Dist: sampleproject (>1.0)
